{
  "id": "recvllSXRNmNu45bx",
  "createdTime": "2022-07-24T07:11:42.000Z",
  "fields": {
    "Slug": "copy-js-expression",
    "Opera": {
      "Main": [
        "recvllSXRNmNu45bx"
      ],
      "GIF": "https://res.cloudinary.com/canidevtools/image/upload/v1658651090/copy-js-path-chrome_hphrin.gif",
      "Video": "https://res.cloudinary.com/canidevtools/video/upload/v1658651084/copy-js-path-chrome_yh3wvj.mp4",
      "Platform": [
        "MacOS",
        "Windows",
        "Linux"
      ],
      "Notes": "1. In the **Elements** tab, right click on the node in the DOM tree > Copy > Copy JS path. This will copy the query selector to the node that can be used in the JS code.\n",
      "Image": "https://res.cloudinary.com/canidevtools/image/upload/v1658651085/copy-js-path-chrome_xpjd6y.png",
      "Name": "Copy as JS expression",
      "LastModified": "2022-07-24T09:09:48.000Z",
      "Category": [
        "Elements"
      ]
    },
    "Name": "Copy as JS expression",
    "Category": "Elements",
    "Description": "Can I copy a node's path to be used as a JavaScript expression?",
    "Edge": {
      "GIF": "https://res.cloudinary.com/canidevtools/image/upload/v1658651673/copy-js-path-edge_kjj5ec.gif",
      "Notes": "1. In the **Elements** tab, right click on the node in the DOM tree > Copy > Copy JS path. This will copy the query selector to the node that can be used in the JS code.\n",
      "Platform": [
        "MacOS",
        "Windows",
        "Linux"
      ],
      "Main": [
        "recvllSXRNmNu45bx"
      ],
      "Image": "https://res.cloudinary.com/canidevtools/image/upload/v1658651755/copy-js-path-edge_yoxudi.png",
      "Name": "Copy as JS expression",
      "Video": "https://res.cloudinary.com/canidevtools/video/upload/v1658651680/copy-js-path-edge_phl2db.mp4",
      "LastModified": "2022-07-24T09:09:45.000Z",
      "Category": [
        "Elements"
      ]
    },
    "Chrome": {
      "References": "[1] Copy JS path, by Chrome DevTools [Docs](https://developer.chrome.com/blog/new-in-devtools-72/#copy)\n",
      "Notes": "1. In the **Elements** tab, right click on the node in the DOM tree > Copy > Copy JS path. This will copy the query selector to the node that can be used in the JS code.\n",
      "Main": [
        "recvllSXRNmNu45bx"
      ],
      "Image": "https://res.cloudinary.com/canidevtools/image/upload/v1658651085/copy-js-path-chrome_xpjd6y.png",
      "Name": "Copy as JS expression",
      "Version": "72-",
      "Video": "https://res.cloudinary.com/canidevtools/video/upload/v1658651084/copy-js-path-chrome_yh3wvj.mp4",
      "GIF": "https://res.cloudinary.com/canidevtools/image/upload/v1658651090/copy-js-path-chrome_hphrin.gif",
      "Platform": [
        "MacOS",
        "Windows",
        "Linux"
      ],
      "LastModified": "2022-07-24T09:09:40.000Z",
      "Category": [
        "Elements"
      ]
    },
    "Related": "copy-css-selector",
    "CreatedTime": "2022-07-24T07:11:42.000Z",
    "LastModifiedTime": "2022-07-24T10:16:01.000Z",
    "Firefox": null,
    "Safari": null
  }
}