{
  "Name": "Emulate blurred vision",
  "Slug": "emulate-blurred-vision",
  "Description": "Can I emulate blurred vision on a page?",
  "Category": "Accessibility",
  "Newsletter": "tips-tricks-3",
  "LastModifiedTime": "2023-03-14T14:18:45.000Z",
  "Author": "@pankajparashar",
  "Chrome": {
    "References": "\n",
    "Notes": "1. Run **Command** (`Cmd+Shift+P` or `Ctrl+Shift+P`) > \"Show Rendering\" (Drawer).\n2. Navigate to the **Emulate vision deficiencies** section and choose \"Blurred vision\".\n",
    "MP4": "https://res.cloudinary.com/canidevtools/video/upload/v1678802960/emulate-blurred-vision-chrome_aj62ff.mp4",
    "Share": "https://twitter.com/CanIDevTools/status/1637145317995937793"
  },
  "Edge": {
    "Notes": "1. Run **Command** (`Cmd+Shift+P` or `Ctrl+Shift+P`) > \"Show Rendering\" (Drawer).\n2. Navigate to the **Emulate** **vision** **deficiencies** section and choose \"Blurred vision\".\n",
    "References": "\n",
    "MP4": "https://res.cloudinary.com/canidevtools/video/upload/v1679160200/emulate-blurred-vision-edge_muhj59.mp4",
    "Share": "https://twitter.com/CanIDevTools/status/1637145317995937793"
  },
  "Opera": {
    "References": "\n",
    "Notes": "1. Run **Command** (`Cmd+Shift+P` or `Ctrl+Shift+P`) > \"Show Rendering\" (Drawer).\n2. Navigate to the **Emulate** **vision** **deficiencies** section and choose \"Blurred vision\".\n",
    "MP4": "https://res.cloudinary.com/canidevtools/video/upload/v1679160201/emulate-blurred-vision-opera_esiiom.mp4",
    "Share": "https://twitter.com/CanIDevTools/status/1637145317995937793"
  }
}