{
  "Chrome": {
    "Notes": "1. Inspect > Select a DOM node.\n2. Open Console > Use $0 to access the currently selected node. Additionally, $1, $2, $3, ... will give you the last selected nodes in the reverse chronological order.\n",
    "Image": "https://res.cloudinary.com/canidevtools/image/upload/v1654325592/Images/get-selected-node-chrome_khtsjk.png",
    "Name": "Get selected node",
    "Platform": [
      "MacOS",
      "Windows",
      "Linux"
    ],
    "Category": [
      "Console"
    ]
  },
  "Firefox": {
    "Image": "https://res.cloudinary.com/canidevtools/image/upload/v1654325592/Images/get-selected-node-firefox_pevlj6.png",
    "Platform": [
      "MacOS",
      "Windows",
      "Linux"
    ],
    "Notes": "1. Inspect > Select a DOM node.\n2. Open Console > Use $0 to access the currently selected node.\n",
    "Name": "Get selected node",
    "Category": [
      "Console"
    ]
  },
  "Edge": {
    "Notes": "1. Inspect > Select a DOM node.\n2. Open Console > Use $0 to access the currently selected node. Additionally, $1, $2, $3, ... will give you the last selected nodes in the reverse chronological order.\n",
    "Platform": [
      "MacOS",
      "Windows",
      "Linux"
    ],
    "Image": "https://res.cloudinary.com/canidevtools/image/upload/v1654325593/Images/get-selected-node-edge_n4wiw9.png",
    "Name": "Get selected node",
    "Category": [
      "Console"
    ]
  },
  "Safari": {
    "Image": "https://res.cloudinary.com/canidevtools/image/upload/v1654325593/Images/get-selected-node-safari_i3ktlm.png",
    "Name": "Get selected node",
    "Platform": [
      "MacOS"
    ],
    "Notes": "1. Inspect > Select a DOM node.\n2. Open Console > Use $0 to access the currently selected node.\n\n",
    "Category": [
      "Console"
    ]
  },
  "Opera": {
    "Platform": [
      "MacOS",
      "Windows",
      "Linux"
    ],
    "Notes": "1. Inspect > Select a DOM node.\n2. Open Console > Use $0 to access the currently selected node. Additionally, $1, $2, $3, ... will give you the last selected nodes in the reverse chronological order.\n",
    "Image": "https://res.cloudinary.com/canidevtools/image/upload/v1654325592/Images/get-selected-node-chrome_khtsjk.png",
    "Name": "Get selected node",
    "Category": [
      "Console"
    ]
  }
}